wbFontParts/__init__.py
wbFontParts/anchor.py
wbFontParts/bPoint.py
wbFontParts/color.py
wbFontParts/component.py
wbFontParts/contour.py
wbFontParts/features.py
wbFontParts/font.py
wbFontParts/glyph.py
wbFontParts/groups.py
wbFontParts/guideline.py
wbFontParts/image.py
wbFontParts/info.py
wbFontParts/kerning.py
wbFontParts/layer.py
wbFontParts/lib.py
wbFontParts/point.py
wbFontParts/segment.py
wbFontParts-0.2.4.dist-info/LICENSE
wbFontParts-0.2.4.dist-info/METADATA
wbFontParts-0.2.4.dist-info/WHEEL
wbFontParts-0.2.4.dist-info/top_level.txt
wbFontParts-0.2.4.dist-info/RECORD
